{"cameraMode":{"drawMode":0,"name":"Shaded","section":"Shading Mode"},"sceneLighting":false,"audioPlay":false,"sceneViewState":{"showFog":true,"showMaterialUpdate":false,"showSkybox":false,"showFlares":true,"showImageEffects":true,"showParticleSystems":true},"in2DMode":false,"pivot":{"x":-2.5716235637664797,"y":0.2900165915489197,"z":-6.232425212860107},"rotation":{"x":-0.40149909257888796,"y":-0.42790496349334719,"z":0.22050794959068299,"w":-0.7791734337806702},"size":6.1948442459106449,"orthographic":false}